django_conn_pool/__init__.py
django_conn_pool/mysql/__init__.py
django_conn_pool/mysql/base.py
django_conn_pool-2.1.0.dist-info/LICENSE
django_conn_pool-2.1.0.dist-info/METADATA
django_conn_pool-2.1.0.dist-info/WHEEL
django_conn_pool-2.1.0.dist-info/top_level.txt
django_conn_pool-2.1.0.dist-info/RECORD
