Metadata-Version: 2.1
Name: django-conn-pool
Version: 2.1.0
Summary: Connection Pooling with Django and SQLAlchemy
Home-page: https://github.com/kerol/django-conn-pool
Author: kerol
Author-email: ikerol@163.com
License: UNKNOWN
Platform: UNKNOWN
Classifier: Programming Language :: Python :: 3
Classifier: License :: OSI Approved :: MIT License
Classifier: Operating System :: OS Independent
Requires-Dist: Django (>2.0.0)
Requires-Dist: SQLAlchemy (>=1.2.7)
